README.md
setup.cfg
setup.py
PyGyverLamp2/PyGyverLamp2.py
PyGyverLamp2/__init__.py
PyGyverLamp2/config.py
PyGyverLamp2/gcolor.py
PyGyverLamp2/test.py
PyGyverLamp2.egg-info/PKG-INFO
PyGyverLamp2.egg-info/SOURCES.txt
PyGyverLamp2.egg-info/dependency_links.txt
PyGyverLamp2.egg-info/requires.txt
PyGyverLamp2.egg-info/top_level.txt