Metadata-Version: 2.1
Name: PyGyverLamp2
Version: 0.1.2
Summary: Python module for control GyverLamp2
Home-page: https://github.com/KirillMonster/PyGyverLamp2
Author: KirillMonster
Author-email: k1rill_monster@mail.ru
License: MIT
Requires-Python: >=3.9
